__init__.py
cdn_rule_engine_sdk/__init__.py
cdn_rule_engine_sdk/rule_engine/Const.py
cdn_rule_engine_sdk/rule_engine/Demo.py
cdn_rule_engine_sdk/rule_engine/Rule.py
cdn_rule_engine_sdk/rule_engine/__init__.py
cdn_rule_engine_sdk-0.0.4.dist-info/licenses/LICENSE
cdn_rule_engine_sdk-0.0.4.dist-info/METADATA
cdn_rule_engine_sdk-0.0.4.dist-info/WHEEL
cdn_rule_engine_sdk-0.0.4.dist-info/top_level.txt
cdn_rule_engine_sdk-0.0.4.dist-info/RECORD
