Metadata-Version: 2.4
Name: cdn_rule_engine_sdk
Version: 0.0.4
Summary: The CDN Rule Engine SDK for Python
Author: CDN SDK
License-Expression: MIT
Project-URL: Homepage, https://github.com/byteplus-sdk/cdn-rule-engine-sdk-python
Classifier: Programming Language :: Python :: 3
Classifier: Operating System :: OS Independent
Requires-Python: >=3.5
License-File: LICENSE
Dynamic: license-file
